microsoft_agents_a365/observability/core/__init__.py
microsoft_agents_a365/observability/core/agent_details.py
microsoft_agents_a365/observability/core/config.py
microsoft_agents_a365/observability/core/constants.py
microsoft_agents_a365/observability/core/execute_tool_scope.py
microsoft_agents_a365/observability/core/execution_type.py
microsoft_agents_a365/observability/core/inference_call_details.py
microsoft_agents_a365/observability/core/inference_operation_type.py
microsoft_agents_a365/observability/core/inference_scope.py
microsoft_agents_a365/observability/core/invoke_agent_details.py
microsoft_agents_a365/observability/core/invoke_agent_scope.py
microsoft_agents_a365/observability/core/opentelemetry_scope.py
microsoft_agents_a365/observability/core/request.py
microsoft_agents_a365/observability/core/source_metadata.py
microsoft_agents_a365/observability/core/tenant_details.py
microsoft_agents_a365/observability/core/tool_call_details.py
microsoft_agents_a365/observability/core/tool_type.py
microsoft_agents_a365/observability/core/utils.py
microsoft_agents_a365/observability/core/exporters/__init__.py
microsoft_agents_a365/observability/core/exporters/agent365_exporter.py
microsoft_agents_a365/observability/core/exporters/agent365_exporter_options.py
microsoft_agents_a365/observability/core/exporters/enriched_span.py
microsoft_agents_a365/observability/core/exporters/enriching_span_processor.py
microsoft_agents_a365/observability/core/exporters/utils.py
microsoft_agents_a365/observability/core/middleware/__init__.py
microsoft_agents_a365/observability/core/middleware/baggage_builder.py
microsoft_agents_a365/observability/core/models/__init__.py
microsoft_agents_a365/observability/core/models/agent_type.py
microsoft_agents_a365/observability/core/models/caller_details.py
microsoft_agents_a365/observability/core/models/operation_source.py
microsoft_agents_a365/observability/core/trace_processor/__init__.py
microsoft_agents_a365_observability_core-0.2.1.dev9.dist-info/METADATA
microsoft_agents_a365_observability_core-0.2.1.dev9.dist-info/WHEEL
microsoft_agents_a365_observability_core-0.2.1.dev9.dist-info/top_level.txt
microsoft_agents_a365_observability_core-0.2.1.dev9.dist-info/RECORD
