Metadata-Version: 2.4
Name: microsoft-agents-a365-observability-core
Version: 0.2.1.dev9
Summary: Telemetry, tracing, and monitoring components for AI agents
Author-email: Microsoft <support@microsoft.com>
License: MIT
Project-URL: Homepage, https://github.com/microsoft/Agent365-python
Project-URL: Repository, https://github.com/microsoft/Agent365-python
Project-URL: Issues, https://github.com/microsoft/Agent365-python/issues
Project-URL: Documentation, https://github.com/microsoft/Agent365-python/tree/main/libraries/microsoft-agents-a365-observability-core
Keywords: observability,telemetry,tracing,opentelemetry,monitoring,ai,agents
Classifier: Development Status :: 3 - Alpha
Classifier: Intended Audience :: Developers
Classifier: Programming Language :: Python :: 3
Classifier: Programming Language :: Python :: 3.11
Classifier: Programming Language :: Python :: 3.12
Classifier: Operating System :: OS Independent
Classifier: Topic :: Software Development :: Libraries :: Python Modules
Classifier: Topic :: Scientific/Engineering :: Artificial Intelligence
Classifier: Topic :: System :: Monitoring
Requires-Python: >=3.11
Requires-Dist: opentelemetry-api>=1.36.0
Requires-Dist: opentelemetry-sdk>=1.36.0
Requires-Dist: opentelemetry-exporter-otlp>=1.36.0
Requires-Dist: pydantic>=2.0.0
Requires-Dist: typing-extensions>=4.0.0
Requires-Dist: microsoft-agents-a365-runtime>=0.0.0
Provides-Extra: azure
Requires-Dist: azure-monitor-opentelemetry-exporter>=1.0.0b39; extra == "azure"
Requires-Dist: azure-identity>=1.12.0; extra == "azure"
Requires-Dist: azure-monitor-ingestion>=1.0.0; extra == "azure"
Provides-Extra: jaeger
Requires-Dist: opentelemetry-exporter-otlp-proto-grpc>=1.36.0; extra == "jaeger"
Provides-Extra: dev
Requires-Dist: pytest>=7.0.0; extra == "dev"
Requires-Dist: pytest-asyncio>=0.21.0; extra == "dev"
Requires-Dist: ruff>=0.1.0; extra == "dev"
Requires-Dist: black>=23.0.0; extra == "dev"
Requires-Dist: mypy>=1.0.0; extra == "dev"
Provides-Extra: test
Requires-Dist: pytest>=7.0.0; extra == "test"
Requires-Dist: pytest-asyncio>=0.21.0; extra == "test"
